CHANGES.txt
README.txt
bootstrap.py
buildout.cfg
setup.py
layout/mockup.png
src/zam/__init__.py
src/zam.skin.egg-info/PKG-INFO
src/zam.skin.egg-info/SOURCES.txt
src/zam.skin.egg-info/dependency_links.txt
src/zam.skin.egg-info/namespace_packages.txt
src/zam.skin.egg-info/not-zip-safe
src/zam.skin.egg-info/requires.txt
src/zam.skin.egg-info/top_level.txt
src/zam/skin/README.txt
src/zam/skin/__init__.py
src/zam/skin/app.zcml
src/zam/skin/configure.zcml
src/zam/skin/ftesting.zcml
src/zam/skin/layer.py
src/zam/skin/layer.zcml
src/zam/skin/menu.zcml
src/zam/skin/menu_global.pt
src/zam/skin/menu_item_global.pt
src/zam/skin/menu_item_site.pt
src/zam/skin/menu_site.pt
src/zam/skin/skin.zcml
src/zam/skin/tests.py
src/zam/skin/browser/__init__.py
src/zam/skin/browser/configure.zcml
src/zam/skin/browser/contents.pt
src/zam/skin/browser/favicon.png
src/zam/skin/browser/index.pt
src/zam/skin/browser/index.py
src/zam/skin/browser/index.zcml
src/zam/skin/browser/sidebar.pt
src/zam/skin/browser/template.pt
src/zam/skin/browser/zam.css
src/zam/skin/browser/divmenu/divMenuArrow.gif
src/zam/skin/browser/divmenu/divMenuArrowOver.gif
src/zam/skin/browser/divmenu/divMenuGrip.gif
src/zam/skin/browser/img/background.gif
src/zam/skin/browser/img/blueBG.gif
src/zam/skin/browser/img/boxBG.jpg
src/zam/skin/browser/img/buttonBG.gif
src/zam/skin/browser/img/buttonBG.png
src/zam/skin/browser/img/collapse.gif
src/zam/skin/browser/img/expand.gif
src/zam/skin/browser/img/folder.gif
src/zam/skin/browser/img/iconContainer.gif
src/zam/skin/browser/img/iconContainer.png
src/zam/skin/browser/img/logo.gif
src/zam/skin/browser/img/logo.png
src/zam/skin/browser/img/menuBG.jpg
src/zam/skin/browser/img/menuBlackBG.gif
src/zam/skin/browser/img/menuBlueBG.gif
src/zam/skin/browser/img/menuGlobalBG.gif
src/zam/skin/browser/img/menuSeparator.gif
src/zam/skin/browser/img/menuTabsLeft.gif
src/zam/skin/browser/img/menuTabsRight.gif
src/zam/skin/browser/img/tableHeaderBG.gif
src/zam/skin/browser/img/topBG.jpg
src/zam/skin/browser/js/divmenu-0.5.0.js
src/zam/skin/browser/js/jquery-1.2.1.min.js
src/zam/skin/browser/js/zam-0.0.1.js